leap_second_client.py
leap_second_client-1.0.dist-info/DESCRIPTION.rst
leap_second_client-1.0.dist-info/METADATA
leap_second_client-1.0.dist-info/RECORD
leap_second_client-1.0.dist-info/WHEEL
leap_second_client-1.0.dist-info/entry_points.txt
leap_second_client-1.0.dist-info/metadata.json
leap_second_client-1.0.dist-info/top_level.txt
